odoo/addons/mrp_progress_button/README.rst
odoo/addons/mrp_progress_button/__init__.py
odoo/addons/mrp_progress_button/__manifest__.py
odoo/addons/mrp_progress_button/i18n/de.po
odoo/addons/mrp_progress_button/i18n/es.po
odoo/addons/mrp_progress_button/i18n/es_MX.po
odoo/addons/mrp_progress_button/i18n/fr.po
odoo/addons/mrp_progress_button/i18n/gl.po
odoo/addons/mrp_progress_button/i18n/hr.po
odoo/addons/mrp_progress_button/i18n/hr_HR.po
odoo/addons/mrp_progress_button/i18n/lt.po
odoo/addons/mrp_progress_button/i18n/mrp_progress_button.pot
odoo/addons/mrp_progress_button/i18n/nl_NL.po
odoo/addons/mrp_progress_button/i18n/pt_BR.po
odoo/addons/mrp_progress_button/i18n/ro.po
odoo/addons/mrp_progress_button/i18n/sl.po
odoo/addons/mrp_progress_button/i18n/tr.po
odoo/addons/mrp_progress_button/i18n/vi_VN.po
odoo/addons/mrp_progress_button/i18n/zh_CN.po
odoo/addons/mrp_progress_button/models/__init__.py
odoo/addons/mrp_progress_button/models/mrp_production.py
odoo/addons/mrp_progress_button/readme/CONTRIBUTORS.rst
odoo/addons/mrp_progress_button/readme/DESCRIPTION.rst
odoo/addons/mrp_progress_button/readme/USAGE.rst
odoo/addons/mrp_progress_button/static/description/icon.png
odoo/addons/mrp_progress_button/static/description/index.html
odoo/addons/mrp_progress_button/tests/__init__.py
odoo/addons/mrp_progress_button/tests/test_progress_button.py
odoo/addons/mrp_progress_button/views/production.xml
odoo11_addon_mrp_progress_button-11.0.1.0.0.99.dev8.dist-info/METADATA
odoo11_addon_mrp_progress_button-11.0.1.0.0.99.dev8.dist-info/WHEEL
odoo11_addon_mrp_progress_button-11.0.1.0.0.99.dev8.dist-info/top_level.txt
odoo11_addon_mrp_progress_button-11.0.1.0.0.99.dev8.dist-info/RECORD
